cell2location/__init__.py
cell2location/run_c2l.py
cell2location/run_colocation.py
cell2location/run_regression.py
cell2location/cluster_averages/__init__.py
cell2location/cluster_averages/cluster_averages.py
cell2location/cluster_averages/markers_by_hierarhy.py
cell2location/cluster_averages/select_features.py
cell2location/distributions/AutoNormalEncoder.py
cell2location/distributions/Gamma.py
cell2location/distributions/NegativeBinomial.py
cell2location/distributions/__init__.py
cell2location/distributions/transforms.py
cell2location/models/README.md
cell2location/models/__init__.py
cell2location/models/_cell2location_model.py
cell2location/models/_cell2location_module.py
cell2location/models/base/__init__.py
cell2location/models/base/_pyro_base_loc_module.py
cell2location/models/base/_pyro_base_reference_module.py
cell2location/models/base/_pyro_mixin.py
cell2location/models/base/base_model.py
cell2location/models/base/pymc3_loc_model.py
cell2location/models/base/pymc3_model.py
cell2location/models/base/regression_torch_model.py
cell2location/models/base/torch_model.py
cell2location/models/downstream/ArchetypalAnalysis.py
cell2location/models/downstream/CoLocatedGroupsSklearnNMF.py
cell2location/models/downstream/__init__.py
cell2location/models/pymc3/LocationModelLinearDependentWMultiExperimentLocationBackgroundNormGeneAlpha.py
cell2location/models/pymc3/LocationModelWTA.py
cell2location/models/pymc3/__init__.py
cell2location/models/pymc3/simplified/LocationModelHierarchicalW.py
cell2location/models/pymc3/simplified/LocationModelHierarchicalWMultiExperiment.py
cell2location/models/pymc3/simplified/LocationModelLinearDependentW.py
cell2location/models/pymc3/simplified/LocationModelLinearDependentWMultiExperiment.py
cell2location/models/pymc3/simplified/LocationModelLinearDependentWMultiExperimentNoMg.py
cell2location/models/pymc3/simplified/LocationModelLinearDependentWMultiExperimentNoSegLs.py
cell2location-0.6a0.dist-info/LICENSE
cell2location-0.6a0.dist-info/METADATA
cell2location-0.6a0.dist-info/WHEEL
cell2location-0.6a0.dist-info/top_level.txt
cell2location-0.6a0.dist-info/RECORD
