Metadata-Version: 2.1
Name: cell2location
Version: 0.6a0
Summary: cell2location: High-throughput spatial mapping of cell types
Home-page: https://github.com/BayraktarLab/cell2location
Author: Vitalii Kleshchevnikov, Artem Shmatko, Emma Dann, Artem Lomakin, Alexander Aivazidis
Author-email: vitalii.kleshchevnikov@sanger.ac.uk
License: Apache License, Version 2.0
Platform: UNKNOWN
Requires-Dist: pyro-ppl (>=1.7.0)
Requires-Dist: scvi-tools (>=0.12.2)
Requires-Dist: torch (>=1.9.0)
Requires-Dist: pymc3 (>=3.8<3.10)
Requires-Dist: arviz (==0.10.0)
Requires-Dist: numpy
Requires-Dist: pandas
Requires-Dist: scanpy
Requires-Dist: plotnine
Provides-Extra: dev
Requires-Dist: black (>=21.4b0) ; extra == 'dev'
Requires-Dist: flake8 ; extra == 'dev'
Requires-Dist: pytest (>=5.0) ; extra == 'dev'
Requires-Dist: pytest-cov ; extra == 'dev'
Requires-Dist: isort ; extra == 'dev'
Requires-Dist: pre-commit ; extra == 'dev'
Provides-Extra: docs
Requires-Dist: sphinx (==3.2.1) ; extra == 'docs'
Requires-Dist: nbsphinx (==0.8.7) ; extra == 'docs'
Requires-Dist: sphinx-rtd-theme (==0.5.2) ; extra == 'docs'
Provides-Extra: tutorials
Requires-Dist: leidenalg (>=0.8.0) ; extra == 'tutorials'
Requires-Dist: python-igraph ; extra == 'tutorials'
